MANIFEST.in
README.md
setup.py
vl_checklist/__init__.py
vl_checklist/data_loader.py
vl_checklist/evaluate.py
vl_checklist/simsunb.ttf
vl_checklist/utils.py
vl_checklist/vlp_model.py
vl_checklist.egg-info/PKG-INFO
vl_checklist.egg-info/SOURCES.txt
vl_checklist.egg-info/dependency_links.txt
vl_checklist.egg-info/requires.txt
vl_checklist.egg-info/top_level.txt