Metadata-Version: 2.1
Name: vl-checklist
Version: 0.0.1
Summary: Checklist for Vision language models
Home-page: https://github.com/om-ai-lab
Author: kyusonglee
License: UNKNOWN
Platform: UNKNOWN
Classifier: Programming Language :: Python :: 3
Classifier: License :: Free for non-commercial use
Classifier: Operating System :: OS Independent
